{
  "type": "Feature",
  "properties": {
    "iso:country":"CA",
    "wof:name":"B1X 1P9",
    "wof:placetype":"postalcode"
},
  "geometry": {"coordinates":[-60.44861,46.313069],"type":"Point"}
}