{
  "type": "Feature",
  "properties": {
    "iso:country":"CA",
    "wof:name":"J0S 1R0",
    "wof:placetype":"postalcode"
},
  "geometry": {"coordinates":[-74.041693,45.105219],"type":"Point"}
}