{
  "type": "Feature",
  "properties": {
    "iso:country":"CA",
    "wof:name":"K1X 1E6",
    "wof:placetype":"postalcode"
},
  "geometry": {"coordinates":[-75.634929,45.272871],"type":"Point"}
}