{
  "type": "Feature",
  "properties": {
    "iso:country":"CA",
    "wof:name":"V0G 2B0",
    "wof:placetype":"postalcode"
},
  "geometry": {"coordinates":[-117.41210700000001,50.276407],"type":"Point"}
}