{
  "type": "Feature",
  "properties": {
    "iso:country":"CA",
    "wof:name":"P0M 2R0",
    "wof:placetype":"postalcode"
},
  "geometry": {"coordinates":[-81.836078,47.457843],"type":"Point"}
}