{
  "type": "Feature",
  "properties": {
    "iso:country":"CA",
    "wof:name":"H4X 1P9",
    "wof:placetype":"postalcode"
},
  "geometry": {"coordinates":[-73.65075400000001,45.453495],"type":"Point"}
}