{
  "type": "Feature",
  "properties": {
    "iso:country":"CA",
    "wof:name":"G0V 1T0",
    "wof:placetype":"postalcode"
},
  "geometry": {"coordinates":[-70.639437,50.291403],"type":"Point"}
}