{
  "type": "Feature",
  "properties": {
    "iso:country":"CA",
    "wof:name":"T0M 1S0",
    "wof:placetype":"postalcode"
},
  "geometry": {"coordinates":[-115.723302,52.078304],"type":"Point"}
}