{
  "type": "Feature",
  "properties": {
    "iso:country":"CA",
    "wof:name":"V8S 3P2",
    "wof:placetype":"postalcode"
},
  "geometry": {"coordinates":[-123.324805,48.418455],"type":"Point"}
}