{
  "type": "Feature",
  "properties": {
    "iso:country":"CA",
    "wof:name":"G0C 1Z0",
    "wof:placetype":"postalcode"
},
  "geometry": {"coordinates":[-65.57554,48.366055],"type":"Point"}
}