{
  "type": "Feature",
  "properties": {
    "iso:country":"CA",
    "wof:name":"B2N 4P8",
    "wof:placetype":"postalcode"
},
  "geometry": {"coordinates":[-63.279434,45.353127],"type":"Point"}
}