{
  "type": "Feature",
  "properties": {
    "iso:country":"CA",
    "wof:name":"G8Y 3S8",
    "wof:placetype":"postalcode"
},
  "geometry": {"coordinates":[-72.59811000000001,46.359023],"type":"Point"}
}