{
  "type": "Feature",
  "properties": {
    "iso:country":"CA",
    "wof:name":"V8K 1H1",
    "wof:placetype":"postalcode"
},
  "geometry": {"coordinates":[-123.495634,48.812225],"type":"Point"}
}