{
  "type": "Feature",
  "properties": {
    "iso:country":"CA",
    "wof:name":"T7E 1W9",
    "wof:placetype":"postalcode"
},
  "geometry": {"coordinates":[-116.538608,53.581783],"type":"Point"}
}