{
  "type": "Feature",
  "properties": {
    "iso:country":"CA",
    "wof:name":"S2V 1A4",
    "wof:placetype":"postalcode"
},
  "geometry": {"coordinates":[-104.895737,50.58487],"type":"Point"}
}