{
  "type": "Feature",
  "properties": {
    "iso:country":"CA",
    "wof:name":"V1T 7N5",
    "wof:placetype":"postalcode"
},
  "geometry": {"coordinates":[-119.284588,50.260952],"type":"Point"}
}