{
  "type": "Feature",
  "properties": {
    "iso:country":"CA",
    "wof:name":"L3V 5E4",
    "wof:placetype":"postalcode"
},
  "geometry": {"coordinates":[-79.390246,44.579391],"type":"Point"}
}