{
  "type": "Feature",
  "properties": {
    "iso:country":"CA",
    "wof:name":"M5V 1Z3",
    "wof:placetype":"postalcode"
},
  "geometry": {"coordinates":[-79.399759,43.641342],"type":"Point"}
}