{
  "type": "Feature",
  "properties": {
    "iso:country":"CA",
    "wof:name":"J3Z 1G9",
    "wof:placetype":"postalcode"
},
  "geometry": {"coordinates":[-73.399748,45.498634],"type":"Point"}
}