{
  "type": "Feature",
  "properties": {
    "iso:country":"CA",
    "wof:name":"V2V 5N2",
    "wof:placetype":"postalcode"
},
  "geometry": {"coordinates":[-122.631102,49.767734],"type":"Point"}
}