{
  "type": "Feature",
  "properties": {
    "iso:country":"CA",
    "wof:name":"K2L 4G2",
    "wof:placetype":"postalcode"
},
  "geometry": {"coordinates":[-75.88952399999999,45.303386],"type":"Point"}
}