{
  "type": "Feature",
  "properties": {
    "iso:country":"CA",
    "wof:name":"K1H 1A5",
    "wof:placetype":"postalcode"
},
  "geometry": {"coordinates":[-75.659308,45.388859],"type":"Point"}
}