{
  "type": "Feature",
  "properties": {
    "iso:country":"CA",
    "wof:name":"R3W 1K7",
    "wof:placetype":"postalcode"
},
  "geometry": {"coordinates":[-97.03778200000001,49.914023],"type":"Point"}
}