{
  "type": "Feature",
  "properties": {
    "iso:country":"CA",
    "wof:name":"M4W 3T5",
    "wof:placetype":"postalcode"
},
  "geometry": {"coordinates":[-79.374616,43.680156],"type":"Point"}
}