{
  "type": "Feature",
  "properties": {
    "iso:country":"CA",
    "wof:name":"T6L 4T4",
    "wof:placetype":"postalcode"
},
  "geometry": {"coordinates":[-113.414012,53.45908],"type":"Point"}
}