{
  "type": "Feature",
  "properties": {
    "iso:country":"CA",
    "wof:name":"V2R 2B5",
    "wof:placetype":"postalcode"
},
  "geometry": {"coordinates":[-122.001705,49.067382],"type":"Point"}
}