{
  "type": "Feature",
  "properties": {
    "iso:country":"CA",
    "wof:name":"E2H 1C9",
    "wof:placetype":"postalcode"
},
  "geometry": {"coordinates":[-66.023025,45.358049],"type":"Point"}
}