{
  "type": "Feature",
  "properties": {
    "iso:country":"CA",
    "wof:name":"E3B 8X4",
    "wof:placetype":"postalcode"
},
  "geometry": {"coordinates":[-66.596547,45.832778],"type":"Point"}
}