{
  "type": "Feature",
  "properties": {
    "iso:country":"CA",
    "wof:name":"G0M 1L0",
    "wof:placetype":"postalcode"
},
  "geometry": {"coordinates":[-70.569706,45.866723],"type":"Point"}
}