{
  "type": "Feature",
  "properties": {
    "iso:country":"CA",
    "wof:name":"N0E 1C0",
    "wof:placetype":"postalcode"
},
  "geometry": {"coordinates":[-80.53720300000001,42.673249],"type":"Point"}
}