{
  "type": "Feature",
  "properties": {
    "iso:country":"CA",
    "wof:name":"T2X 1H9",
    "wof:placetype":"postalcode"
},
  "geometry": {"coordinates":[-114.031684,50.886611],"type":"Point"}
}