{
  "type": "Feature",
  "properties": {
    "iso:country":"CA",
    "wof:name":"V3R 9W8",
    "wof:placetype":"postalcode"
},
  "geometry": {"coordinates":[-122.806721,49.200687],"type":"Point"}
}