{
  "type": "Feature",
  "properties": {
    "iso:country":"CA",
    "wof:name":"V2A 4K6",
    "wof:placetype":"postalcode"
},
  "geometry": {"coordinates":[-119.67589,49.469104],"type":"Point"}
}