{
  "type": "Feature",
  "properties": {
    "iso:country":"CA",
    "wof:name":"J8Y 2L7",
    "wof:placetype":"postalcode"
},
  "geometry": {"coordinates":[-75.73769,45.446865],"type":"Point"}
}