{
  "type": "Feature",
  "properties": {
    "iso:country":"CA",
    "wof:name":"E5A 1H9",
    "wof:placetype":"postalcode"
},
  "geometry": {"coordinates":[-67.169101,45.39629],"type":"Point"}
}