{
  "type": "Feature",
  "properties": {
    "iso:country":"CA",
    "wof:name":"V9S 3M9",
    "wof:placetype":"postalcode"
},
  "geometry": {"coordinates":[-123.975312,49.188647],"type":"Point"}
}