{
  "type": "Feature",
  "properties": {
    "iso:country":"CA",
    "wof:name":"T6E 3Y9",
    "wof:placetype":"postalcode"
},
  "geometry": {"coordinates":[-113.47483,53.495434],"type":"Point"}
}