{
  "type": "Feature",
  "properties": {
    "iso:country":"CA",
    "wof:name":"H4R 1S6",
    "wof:placetype":"postalcode"
},
  "geometry": {"coordinates":[-73.713684,45.504514],"type":"Point"}
}