{
  "type": "Feature",
  "properties": {
    "iso:country":"CA",
    "wof:name":"V6B 6R5",
    "wof:placetype":"postalcode"
},
  "geometry": {"coordinates":[-123.111334,49.28012],"type":"Point"}
}