{
  "type": "Feature",
  "properties": {
    "iso:country":"CA",
    "wof:name":"G8K 1J5",
    "wof:placetype":"postalcode"
},
  "geometry": {"coordinates":[-72.45557700000001,48.700422],"type":"Point"}
}