{
  "type": "Feature",
  "properties": {
    "iso:country":"CA",
    "wof:name":"E5T 1L6",
    "wof:placetype":"postalcode"
},
  "geometry": {"coordinates":[-65.954899,45.675363],"type":"Point"}
}