{
  "type": "Feature",
  "properties": {
    "iso:country":"CA",
    "wof:name":"M5G 1R8",
    "wof:placetype":"postalcode"
},
  "geometry": {"coordinates":[-79.386653,43.657246],"type":"Point"}
}