{
  "type": "Feature",
  "properties": {
    "iso:country":"CA",
    "wof:name":"J1E 2K2",
    "wof:placetype":"postalcode"
},
  "geometry": {"coordinates":[-71.869478,45.423763],"type":"Point"}
}