{
  "type": "Feature",
  "properties": {
    "iso:country":"CA",
    "wof:name":"T4E 1C3",
    "wof:placetype":"postalcode"
},
  "geometry": {"coordinates":[-113.70319499999999,52.214212],"type":"Point"}
}