{
  "type": "Feature",
  "properties": {
    "iso:country":"CA",
    "wof:name":"K1S 2N4",
    "wof:placetype":"postalcode"
},
  "geometry": {"coordinates":[-75.68778,45.399473],"type":"Point"}
}