{
  "type": "Feature",
  "properties": {
    "iso:country":"CA",
    "wof:name":"P0X 1B0",
    "wof:placetype":"postalcode"
},
  "geometry": {"coordinates":[-92.273633,51.121211],"type":"Point"}
}