{
  "type": "Feature",
  "properties": {
    "iso:country":"CA",
    "wof:name":"R3C 2J1",
    "wof:placetype":"postalcode"
},
  "geometry": {"coordinates":[-97.26186,50.009781],"type":"Point"}
}