{
  "type": "Feature",
  "properties": {
    "iso:country":"CA",
    "wof:name":"A2N 3V3",
    "wof:placetype":"postalcode"
},
  "geometry": {"coordinates":[-58.564897,48.556631],"type":"Point"}
}