{
  "type": "Feature",
  "properties": {
    "iso:country":"CA",
    "wof:name":"J2R 1N4",
    "wof:placetype":"postalcode"
},
  "geometry": {"coordinates":[-72.875957,45.646448],"type":"Point"}
}