{
  "type": "Feature",
  "properties": {
    "iso:country":"CA",
    "wof:name":"H3M 3A9",
    "wof:placetype":"postalcode"
},
  "geometry": {"coordinates":[-73.691569,45.537252],"type":"Point"}
}