{
  "type": "Feature",
  "properties": {
    "iso:country":"CA",
    "wof:name":"Y0A 1C0",
    "wof:placetype":"postalcode"
},
  "geometry": {"coordinates":[-130.70691400000001,61.397516],"type":"Point"}
}