{
  "type": "Feature",
  "properties": {
    "iso:country":"CA",
    "wof:name":"T1X 1L3",
    "wof:placetype":"postalcode"
},
  "geometry": {"coordinates":[-113.797876,50.90847],"type":"Point"}
}