{
  "type": "Feature",
  "properties": {
    "iso:country":"CA",
    "wof:name":"G3J 1E7",
    "wof:placetype":"postalcode"
},
  "geometry": {"coordinates":[-71.461658,46.869945],"type":"Point"}
}