{
  "type": "Feature",
  "properties": {
    "iso:country":"CA",
    "wof:name":"T0C 1B0",
    "wof:placetype":"postalcode"
},
  "geometry": {"coordinates":[-111.197869,52.039494],"type":"Point"}
}