{
  "type": "Feature",
  "properties": {
    "iso:country":"CA",
    "wof:name":"E2S 1G7",
    "wof:placetype":"postalcode"
},
  "geometry": {"coordinates":[-65.781389,45.331549],"type":"Point"}
}