{
  "type": "Feature",
  "properties": {
    "iso:country":"CA",
    "wof:name":"R0H 1A0",
    "wof:placetype":"postalcode"
},
  "geometry": {"coordinates":[-98.53001500000001,50.54839],"type":"Point"}
}