{
  "type": "Feature",
  "properties": {
    "iso:country":"CA",
    "wof:name":"H1G 1N8",
    "wof:placetype":"postalcode"
},
  "geometry": {"coordinates":[-73.622491,45.612915],"type":"Point"}
}