{
  "type": "Feature",
  "properties": {
    "iso:country":"CA",
    "wof:name":"E9E 1Y6",
    "wof:placetype":"postalcode"
},
  "geometry": {"coordinates":[-66.62200900000001,47.092837],"type":"Point"}
}