{
  "type": "Feature",
  "properties": {
    "iso:country":"CA",
    "wof:name":"L7R 2T4",
    "wof:placetype":"postalcode"
},
  "geometry": {"coordinates":[-79.848024,43.385555],"type":"Point"}
}