{
  "type": "Feature",
  "properties": {
    "iso:country":"CA",
    "wof:name":"T9H 3L2",
    "wof:placetype":"postalcode"
},
  "geometry": {"coordinates":[-110.60736799999999,56.848513],"type":"Point"}
}