{
  "type": "Feature",
  "properties": {
    "iso:country":"CA",
    "wof:name":"J1R 0J6",
    "wof:placetype":"postalcode"
},
  "geometry": {"coordinates":[-72.035365,45.398549],"type":"Point"}
}