{
  "type": "Feature",
  "properties": {
    "iso:country":"CA",
    "wof:name":"M6J 2G9",
    "wof:placetype":"postalcode"
},
  "geometry": {"coordinates":[-79.413855,43.648806],"type":"Point"}
}