{
  "type": "Feature",
  "properties": {
    "iso:country":"CA",
    "wof:name":"V8V 3S2",
    "wof:placetype":"postalcode"
},
  "geometry": {"coordinates":[-123.361142,48.41415],"type":"Point"}
}