{
  "type": "Feature",
  "properties": {
    "iso:country":"CA",
    "wof:name":"T0A 0V1",
    "wof:placetype":"postalcode"
},
  "geometry": {"coordinates":[-111.901309,54.820922],"type":"Point"}
}