{
  "type": "Feature",
  "properties": {
    "iso:country":"CA",
    "wof:name":"R3M 0E2",
    "wof:placetype":"postalcode"
},
  "geometry": {"coordinates":[-97.165941,49.862614],"type":"Point"}
}