{
  "type": "Feature",
  "properties": {
    "iso:country":"CA",
    "wof:name":"E8T 1P5",
    "wof:placetype":"postalcode"
},
  "geometry": {"coordinates":[-64.622899,47.837523],"type":"Point"}
}