{
  "type": "Feature",
  "properties": {
    "iso:country":"CA",
    "wof:name":"L1H 2J9",
    "wof:placetype":"postalcode"
},
  "geometry": {"coordinates":[-78.900423,44.004713],"type":"Point"}
}