{
  "type": "Feature",
  "properties": {
    "iso:country":"CA",
    "wof:name":"R2L 0E7",
    "wof:placetype":"postalcode"
},
  "geometry": {"coordinates":[-97.100032,49.906313],"type":"Point"}
}