{
  "type": "Feature",
  "properties": {
    "iso:country":"CA",
    "wof:name":"K1K 2N5",
    "wof:placetype":"postalcode"
},
  "geometry": {"coordinates":[-75.63777399999999,45.450287],"type":"Point"}
}