{
  "type": "Feature",
  "properties": {
    "iso:country":"CA",
    "wof:name":"L7N 1N1",
    "wof:placetype":"postalcode"
},
  "geometry": {"coordinates":[-79.78430400000001,43.350699],"type":"Point"}
}