{
  "type": "Feature",
  "properties": {
    "iso:country":"CA",
    "wof:name":"V8A 1Y5",
    "wof:placetype":"postalcode"
},
  "geometry": {"coordinates":[-124.346456,49.989374],"type":"Point"}
}