{
  "type": "Feature",
  "properties": {
    "iso:country":"CA",
    "wof:name":"N8Y 3E7",
    "wof:placetype":"postalcode"
},
  "geometry": {"coordinates":[-82.992932,42.316358],"type":"Point"}
}