{
  "type": "Feature",
  "properties": {
    "iso:country":"CA",
    "wof:name":"C1B 1H1",
    "wof:placetype":"postalcode"
},
  "geometry": {"coordinates":[-63.09413,46.21797],"type":"Point"}
}