{
  "type": "Feature",
  "properties": {
    "iso:country":"CA",
    "wof:name":"S7P 0A1",
    "wof:placetype":"postalcode"
},
  "geometry": {"coordinates":[-106.527545,52.24711],"type":"Point"}
}