{
  "type": "Feature",
  "properties": {
    "iso:country":"CA",
    "wof:name":"E6B 1A7",
    "wof:placetype":"postalcode"
},
  "geometry": {"coordinates":[-66.877765,46.300654],"type":"Point"}
}