{
  "type": "Feature",
  "properties": {
    "iso:country":"CA",
    "wof:name":"J6V 1K9",
    "wof:placetype":"postalcode"
},
  "geometry": {"coordinates":[-73.535618,45.71302],"type":"Point"}
}