{
  "type": "Feature",
  "properties": {
    "iso:country":"CA",
    "wof:name":"E1H 1A4",
    "wof:placetype":"postalcode"
},
  "geometry": {"coordinates":[-64.753851,46.177202],"type":"Point"}
}