{
  "type": "Feature",
  "properties": {
    "iso:country":"CA",
    "wof:name":"T2G 3W6",
    "wof:placetype":"postalcode"
},
  "geometry": {"coordinates":[-114.027097,51.027393],"type":"Point"}
}