{
  "type": "Feature",
  "properties": {
    "iso:country":"CA",
    "wof:name":"P2B 2R8",
    "wof:placetype":"postalcode"
},
  "geometry": {"coordinates":[-79.88549999999999,46.411256],"type":"Point"}
}