{
  "type": "Feature",
  "properties": {
    "iso:country":"CA",
    "wof:name":"N8W 3S3",
    "wof:placetype":"postalcode"
},
  "geometry": {"coordinates":[-82.971349,42.289393],"type":"Point"}
}