{
  "type": "Feature",
  "properties": {
    "iso:country":"CA",
    "wof:name":"N2H 1A1",
    "wof:placetype":"postalcode"
},
  "geometry": {"coordinates":[-80.483501,43.461889],"type":"Point"}
}