{
  "type": "Feature",
  "properties": {
    "iso:country":"CA",
    "wof:name":"P3Y 1N5",
    "wof:placetype":"postalcode"
},
  "geometry": {"coordinates":[-81.13422799999999,46.457723],"type":"Point"}
}