{
  "type": "Feature",
  "properties": {
    "iso:country":"CA",
    "wof:name":"B2C 1C5",
    "wof:placetype":"postalcode"
},
  "geometry": {"coordinates":[-60.843621,45.988513],"type":"Point"}
}