{
  "type": "Feature",
  "properties": {
    "iso:country":"CA",
    "wof:name":"E4A 3K9",
    "wof:placetype":"postalcode"
},
  "geometry": {"coordinates":[-65.81442,46.175559],"type":"Point"}
}