{
  "type": "Feature",
  "properties": {
    "iso:country":"CA",
    "wof:name":"J3V 3Y4",
    "wof:placetype":"postalcode"
},
  "geometry": {"coordinates":[-73.344573,45.536685],"type":"Point"}
}