{
  "type": "Feature",
  "properties": {
    "iso:country":"CA",
    "wof:name":"V8R 1L4",
    "wof:placetype":"postalcode"
},
  "geometry": {"coordinates":[-123.32071000000001,48.436232],"type":"Point"}
}