{
  "type": "Feature",
  "properties": {
    "iso:country":"CA",
    "wof:name":"H1Z 1J7",
    "wof:placetype":"postalcode"
},
  "geometry": {"coordinates":[-73.62209,45.569372],"type":"Point"}
}