{
  "type": "Feature",
  "properties": {
    "iso:country":"CA",
    "wof:name":"V6L 3A8",
    "wof:placetype":"postalcode"
},
  "geometry": {"coordinates":[-123.165791,49.249675],"type":"Point"}
}