{
  "type": "Feature",
  "properties": {
    "iso:country":"CA",
    "wof:name":"J0H 2B0",
    "wof:placetype":"postalcode"
},
  "geometry": {"coordinates":[-72.712067,45.644288],"type":"Point"}
}