{
  "type": "Feature",
  "properties": {
    "iso:country":"CA",
    "wof:name":"G8J 1L1",
    "wof:placetype":"postalcode"
},
  "geometry": {"coordinates":[-73.440527,48.77329],"type":"Point"}
}