{
  "type": "Feature",
  "properties": {
    "iso:country":"CA",
    "wof:name":"P1B 3W4",
    "wof:placetype":"postalcode"
},
  "geometry": {"coordinates":[-79.614199,46.332069],"type":"Point"}
}