{
  "type": "Feature",
  "properties": {
    "iso:country":"CA",
    "wof:name":"L6P 1R6",
    "wof:placetype":"postalcode"
},
  "geometry": {"coordinates":[-79.70124,43.795132],"type":"Point"}
}