{
  "type": "Feature",
  "properties": {
    "iso:country":"CA",
    "wof:name":"N5V 3P9",
    "wof:placetype":"postalcode"
},
  "geometry": {"coordinates":[-81.154878,43.024111],"type":"Point"}
}