{
  "type": "Feature",
  "properties": {
    "iso:country":"CA",
    "wof:name":"G6T 2C5",
    "wof:placetype":"postalcode"
},
  "geometry": {"coordinates":[-71.98427,46.089006],"type":"Point"}
}