{
  "type": "Feature",
  "properties": {
    "iso:country":"CA",
    "wof:name":"J5T 2X4",
    "wof:placetype":"postalcode"
},
  "geometry": {"coordinates":[-73.32611900000001,45.904576],"type":"Point"}
}