{
  "type": "Feature",
  "properties": {
    "iso:country":"CA",
    "wof:name":"T4X 1B1",
    "wof:placetype":"postalcode"
},
  "geometry": {"coordinates":[-113.415087,53.352219],"type":"Point"}
}