{
  "type": "Feature",
  "properties": {
    "iso:country":"CA",
    "wof:name":"G3G 1A7",
    "wof:placetype":"postalcode"
},
  "geometry": {"coordinates":[-71.38601300000001,46.909792],"type":"Point"}
}