{
  "type": "Feature",
  "properties": {
    "iso:country":"CA",
    "wof:name":"H7T 1P4",
    "wof:placetype":"postalcode"
},
  "geometry": {"coordinates":[-73.771967,45.55667],"type":"Point"}
}