{
  "type": "Feature",
  "properties": {
    "iso:country":"CA",
    "wof:name":"N5R 3N5",
    "wof:placetype":"postalcode"
},
  "geometry": {"coordinates":[-81.185941,42.756535],"type":"Point"}
}