{
  "type": "Feature",
  "properties": {
    "iso:country":"CA",
    "wof:name":"L3S 2A4",
    "wof:placetype":"postalcode"
},
  "geometry": {"coordinates":[-79.260963,43.848126],"type":"Point"}
}