{
  "type": "Feature",
  "properties": {
    "iso:country":"CA",
    "wof:name":"J5X 4N6",
    "wof:placetype":"postalcode"
},
  "geometry": {"coordinates":[-73.505799,45.850254],"type":"Point"}
}