{
  "type": "Feature",
  "properties": {
    "iso:country":"CA",
    "wof:name":"T4V 1K2",
    "wof:placetype":"postalcode"
},
  "geometry": {"coordinates":[-112.83411700000001,53.114777],"type":"Point"}
}