{
  "type": "Feature",
  "properties": {
    "iso:country":"CA",
    "wof:name":"P3E 4B6",
    "wof:placetype":"postalcode"
},
  "geometry": {"coordinates":[-80.83685199999999,46.247741],"type":"Point"}
}