{
  "type": "Feature",
  "properties": {
    "iso:country":"CA",
    "wof:name":"H4M 2Y8",
    "wof:placetype":"postalcode"
},
  "geometry": {"coordinates":[-73.68696,45.498531],"type":"Point"}
}