{
  "type": "Feature",
  "properties": {
    "iso:country":"CA",
    "wof:name":"G0T 1W0",
    "wof:placetype":"postalcode"
},
  "geometry": {"coordinates":[-69.568926,48.977781],"type":"Point"}
}