{
  "type": "Feature",
  "properties": {
    "iso:country":"CA",
    "wof:name":"T6X 1K6",
    "wof:placetype":"postalcode"
},
  "geometry": {"coordinates":[-113.43403600000001,53.415785],"type":"Point"}
}