{
  "type": "Feature",
  "properties": {
    "iso:country":"CA",
    "wof:name":"T5B 4C1",
    "wof:placetype":"postalcode"
},
  "geometry": {"coordinates":[-113.322686,53.745307],"type":"Point"}
}