{
  "type": "Feature",
  "properties": {
    "iso:country":"CA",
    "wof:name":"E8J 2A5",
    "wof:placetype":"postalcode"
},
  "geometry": {"coordinates":[-65.81995000000001,47.794921],"type":"Point"}
}