{
  "type": "Feature",
  "properties": {
    "iso:country":"CA",
    "wof:name":"T3Z 1G2",
    "wof:placetype":"postalcode"
},
  "geometry": {"coordinates":[-114.362257,51.070592],"type":"Point"}
}