{
  "type": "Feature",
  "properties": {
    "iso:country":"CA",
    "wof:name":"E5R 1L6",
    "wof:placetype":"postalcode"
},
  "geometry": {"coordinates":[-65.504813,45.432196],"type":"Point"}
}