{
  "type": "Feature",
  "properties": {
    "iso:country":"CA",
    "wof:name":"N1L 1P9",
    "wof:placetype":"postalcode"
},
  "geometry": {"coordinates":[-80.17711199999999,43.501759],"type":"Point"}
}