{
  "type": "Feature",
  "properties": {
    "iso:country":"CA",
    "wof:name":"V5R 5R7",
    "wof:placetype":"postalcode"
},
  "geometry": {"coordinates":[-123.040502,49.239948],"type":"Point"}
}