{
  "type": "Feature",
  "properties": {
    "iso:country":"CA",
    "wof:name":"T5E 4G8",
    "wof:placetype":"postalcode"
},
  "geometry": {"coordinates":[-113.427609,53.771437],"type":"Point"}
}