{
  "type": "Feature",
  "properties": {
    "iso:country":"CA",
    "wof:name":"B3L 3X1",
    "wof:placetype":"postalcode"
},
  "geometry": {"coordinates":[-63.614892,44.65037],"type":"Point"}
}