{
  "type": "Feature",
  "properties": {
    "iso:country":"CA",
    "wof:name":"E8P 1B6",
    "wof:placetype":"postalcode"
},
  "geometry": {"coordinates":[-64.912193,47.700704],"type":"Point"}
}