{
  "type": "Feature",
  "properties": {
    "iso:country":"CA",
    "wof:name":"J3N 1L6",
    "wof:placetype":"postalcode"
},
  "geometry": {"coordinates":[-73.275085,45.521557],"type":"Point"}
}