{
  "type": "Feature",
  "properties": {
    "iso:country":"CA",
    "wof:name":"S4R 3N1",
    "wof:placetype":"postalcode"
},
  "geometry": {"coordinates":[-104.61147699999999,50.483866],"type":"Point"}
}