{
  "type": "Feature",
  "properties": {
    "iso:country":"CA",
    "wof:name":"L9J 1C1",
    "wof:placetype":"postalcode"
},
  "geometry": {"coordinates":[-79.595786,44.351373],"type":"Point"}
}