{
  "type": "Feature",
  "properties": {
    "iso:country":"CA",
    "wof:name":"J2X 1K8",
    "wof:placetype":"postalcode"
},
  "geometry": {"coordinates":[-73.21407600000001,45.292567],"type":"Point"}
}