{
  "type": "Feature",
  "properties": {
    "iso:country":"CA",
    "wof:name":"A0H 2C0",
    "wof:placetype":"postalcode"
},
  "geometry": {"coordinates":[-56.60072,48.553248],"type":"Point"}
}