{
  "type": "Feature",
  "properties": {
    "iso:country":"CA",
    "wof:name":"M9L 1X5",
    "wof:placetype":"postalcode"
},
  "geometry": {"coordinates":[-79.54702,43.762474],"type":"Point"}
}