{
  "type": "Feature",
  "properties": {
    "iso:country":"CA",
    "wof:name":"J7E 1V1",
    "wof:placetype":"postalcode"
},
  "geometry": {"coordinates":[-73.83660399999999,45.640488],"type":"Point"}
}