{
  "type": "Feature",
  "properties": {
    "iso:country":"CA",
    "wof:name":"L4G 2C1",
    "wof:placetype":"postalcode"
},
  "geometry": {"coordinates":[-79.447473,43.99657],"type":"Point"}
}