{
  "type": "Feature",
  "properties": {
    "iso:country":"CA",
    "wof:name":"B4N 1G9",
    "wof:placetype":"postalcode"
},
  "geometry": {"coordinates":[-64.540181,44.947544],"type":"Point"}
}