{
  "type": "Feature",
  "properties": {
    "iso:country":"CA",
    "wof:name":"H9R 3A5",
    "wof:placetype":"postalcode"
},
  "geometry": {"coordinates":[-73.813062,45.460037],"type":"Point"}
}