{
  "type": "Feature",
  "properties": {
    "iso:country":"CA",
    "wof:name":"T9V 1C2",
    "wof:placetype":"postalcode"
},
  "geometry": {"coordinates":[-110.093568,53.205128],"type":"Point"}
}