{
  "type": "Feature",
  "properties": {
    "iso:country":"CA",
    "wof:name":"G1T 2C2",
    "wof:placetype":"postalcode"
},
  "geometry": {"coordinates":[-71.26086599999999,46.77477],"type":"Point"}
}