{
  "type": "Feature",
  "properties": {
    "iso:country":"CA",
    "wof:name":"V9J 1N2",
    "wof:placetype":"postalcode"
},
  "geometry": {"coordinates":[-125.255622,49.730138],"type":"Point"}
}