{
  "type": "Feature",
  "properties": {
    "iso:country":"CA",
    "wof:name":"J9T 3V4",
    "wof:placetype":"postalcode"
},
  "geometry": {"coordinates":[-77.96022499999999,48.653981],"type":"Point"}
}