{
  "type": "Feature",
  "properties": {
    "iso:country":"CA",
    "wof:name":"T8C 1B7",
    "wof:placetype":"postalcode"
},
  "geometry": {"coordinates":[-113.195223,53.439559],"type":"Point"}
}