{
  "type": "Feature",
  "properties": {
    "iso:country":"CA",
    "wof:name":"M6G 3Z4",
    "wof:placetype":"postalcode"
},
  "geometry": {"coordinates":[-79.420351,43.668236],"type":"Point"}
}