{
  "type": "Feature",
  "properties": {
    "iso:country":"CA",
    "wof:name":"H9J 2X5",
    "wof:placetype":"postalcode"
},
  "geometry": {"coordinates":[-73.87256600000001,45.45245],"type":"Point"}
}