{
  "type": "Feature",
  "properties": {
    "iso:country":"CA",
    "wof:name":"J7T 3B6",
    "wof:placetype":"postalcode"
},
  "geometry": {"coordinates":[-74.137984,45.378322],"type":"Point"}
}