{
  "type": "Feature",
  "properties": {
    "iso:country":"CA",
    "wof:name":"H2V 1H4",
    "wof:placetype":"postalcode"
},
  "geometry": {"coordinates":[-73.607196,45.516834],"type":"Point"}
}