{
  "type": "Feature",
  "properties": {
    "iso:country":"CA",
    "wof:name":"J6R 1P6",
    "wof:placetype":"postalcode"
},
  "geometry": {"coordinates":[-73.74111600000001,45.308098],"type":"Point"}
}