{
  "type": "Feature",
  "properties": {
    "iso:country":"CA",
    "wof:name":"L4W 4A1",
    "wof:placetype":"postalcode"
},
  "geometry": {"coordinates":[-79.622146,43.635168],"type":"Point"}
}