{
  "type": "Feature",
  "properties": {
    "iso:country":"CA",
    "wof:name":"J6N 3C6",
    "wof:placetype":"postalcode"
},
  "geometry": {"coordinates":[-73.856038,45.288393],"type":"Point"}
}