{
  "type": "Feature",
  "properties": {
    "iso:country":"CA",
    "wof:name":"N1G 4V8",
    "wof:placetype":"postalcode"
},
  "geometry": {"coordinates":[-80.22960399999999,43.522488],"type":"Point"}
}