{
  "type": "Feature",
  "properties": {
    "iso:country":"CA",
    "wof:name":"J3Y 1V1",
    "wof:placetype":"postalcode"
},
  "geometry": {"coordinates":[-73.384677,45.468606],"type":"Point"}
}