{
  "type": "Feature",
  "properties": {
    "iso:country":"CA",
    "wof:name":"T5H 3N7",
    "wof:placetype":"postalcode"
},
  "geometry": {"coordinates":[-113.479944,53.55041],"type":"Point"}
}