{
  "type": "Feature",
  "properties": {
    "iso:country":"CA",
    "wof:name":"G2J 1B8",
    "wof:placetype":"postalcode"
},
  "geometry": {"coordinates":[-71.276832,46.838208],"type":"Point"}
}