{
  "type": "Feature",
  "properties": {
    "iso:country":"CA",
    "wof:name":"N2L 4Z5",
    "wof:placetype":"postalcode"
},
  "geometry": {"coordinates":[-80.54582499999999,43.473049],"type":"Point"}
}