{
  "type": "Feature",
  "properties": {
    "iso:country":"CA",
    "wof:name":"L4M 2A7",
    "wof:placetype":"postalcode"
},
  "geometry": {"coordinates":[-79.674786,44.480363],"type":"Point"}
}