{
  "type": "Feature",
  "properties": {
    "iso:country":"CA",
    "wof:name":"V8Y 2L4",
    "wof:placetype":"postalcode"
},
  "geometry": {"coordinates":[-123.376205,48.52639],"type":"Point"}
}