{
  "type": "Feature",
  "properties": {
    "iso:country":"CA",
    "wof:name":"T1W 3L8",
    "wof:placetype":"postalcode"
},
  "geometry": {"coordinates":[-115.322542,51.443783],"type":"Point"}
}