{
  "type": "Feature",
  "properties": {
    "iso:country":"CA",
    "wof:name":"T8S 1S9",
    "wof:placetype":"postalcode"
},
  "geometry": {"coordinates":[-117.376711,56.268442],"type":"Point"}
}