{
  "type": "Feature",
  "properties": {
    "iso:country":"CA",
    "wof:name":"M5N 1L4",
    "wof:placetype":"postalcode"
},
  "geometry": {"coordinates":[-79.418648,43.710815],"type":"Point"}
}