{
  "type": "Feature",
  "properties": {
    "iso:country":"CA",
    "wof:name":"V1P 1N7",
    "wof:placetype":"postalcode"
},
  "geometry": {"coordinates":[-119.147723,49.920083],"type":"Point"}
}