{
  "type": "Feature",
  "properties": {
    "iso:country":"CA",
    "wof:name":"B1K 1W3",
    "wof:placetype":"postalcode"
},
  "geometry": {"coordinates":[-60.273533,45.879478],"type":"Point"}
}