{
  "type": "Feature",
  "properties": {
    "iso:country":"CA",
    "wof:name":"R2C 3L7",
    "wof:placetype":"postalcode"
},
  "geometry": {"coordinates":[-96.93525200000001,49.946378],"type":"Point"}
}