{
  "type": "Feature",
  "properties": {
    "iso:country":"CA",
    "wof:name":"A0A 4C0",
    "wof:placetype":"postalcode"
},
  "geometry": {"coordinates":[-53.131125,46.888359],"type":"Point"}
}