{
  "type": "Feature",
  "properties": {
    "iso:country":"CA",
    "wof:name":"L4R 1Z1",
    "wof:placetype":"postalcode"
},
  "geometry": {"coordinates":[-79.875885,44.73052],"type":"Point"}
}