{
  "type": "Feature",
  "properties": {
    "iso:country":"CA",
    "wof:name":"L4L 6N2",
    "wof:placetype":"postalcode"
},
  "geometry": {"coordinates":[-79.571956,43.797402],"type":"Point"}
}