{
  "type": "Feature",
  "properties": {
    "iso:country":"CA",
    "wof:name":"J6Z 2X1",
    "wof:placetype":"postalcode"
},
  "geometry": {"coordinates":[-73.774951,45.668055],"type":"Point"}
}