{
  "type": "Feature",
  "properties": {
    "iso:country":"CA",
    "wof:name":"R1B 1A4",
    "wof:placetype":"postalcode"
},
  "geometry": {"coordinates":[-96.935044,50.083945],"type":"Point"}
}