{
  "type": "Feature",
  "properties": {
    "iso:country":"CA",
    "wof:name":"H7M 3X3",
    "wof:placetype":"postalcode"
},
  "geometry": {"coordinates":[-73.715508,45.599829],"type":"Point"}
}