{
  "type": "Feature",
  "properties": {
    "iso:country":"CA",
    "wof:name":"C1E 1P3",
    "wof:placetype":"postalcode"
},
  "geometry": {"coordinates":[-63.202429,46.340104],"type":"Point"}
}