{
  "type": "Feature",
  "properties": {
    "iso:country":"CA",
    "wof:name":"J8L 2B5",
    "wof:placetype":"postalcode"
},
  "geometry": {"coordinates":[-75.380674,45.734238],"type":"Point"}
}