{
  "type": "Feature",
  "properties": {
    "iso:country":"CA",
    "wof:name":"E7N 2W6",
    "wof:placetype":"postalcode"
},
  "geometry": {"coordinates":[-67.65810399999999,45.993735],"type":"Point"}
}