{
  "type": "Feature",
  "properties": {
    "iso:country":"CA",
    "wof:name":"J2J 2W3",
    "wof:placetype":"postalcode"
},
  "geometry": {"coordinates":[-72.79247100000001,45.396976],"type":"Point"}
}