{
  "type": "Feature",
  "properties": {
    "iso:country":"CA",
    "wof:name":"L0E 1A0",
    "wof:placetype":"postalcode"
},
  "geometry": {"coordinates":[-79.308958,44.334643],"type":"Point"}
}