{
  "type": "Feature",
  "properties": {
    "iso:country":"CA",
    "wof:name":"H1C 0A3",
    "wof:placetype":"postalcode"
},
  "geometry": {"coordinates":[-73.53619500000001,45.66064],"type":"Point"}
}