{
  "type": "Feature",
  "properties": {
    "iso:country":"CA",
    "wof:name":"G0R 1Z0",
    "wof:placetype":"postalcode"
},
  "geometry": {"coordinates":[-70.31276800000001,46.659643],"type":"Point"}
}