{
  "type": "Feature",
  "properties": {
    "iso:country":"CA",
    "wof:name":"E9G 1Z7",
    "wof:placetype":"postalcode"
},
  "geometry": {"coordinates":[-65.293352,47.239818],"type":"Point"}
}