{
  "type": "Feature",
  "properties": {
    "iso:country":"CA",
    "wof:name":"E5L 2M8",
    "wof:placetype":"postalcode"
},
  "geometry": {"coordinates":[-66.67142699999999,45.517344],"type":"Point"}
}