{
  "type": "Feature",
  "properties": {
    "iso:country":"CA",
    "wof:name":"G4S 1M7",
    "wof:placetype":"postalcode"
},
  "geometry": {"coordinates":[-66.37273999999999,50.273694],"type":"Point"}
}