{
  "type": "Feature",
  "properties": {
    "iso:country":"CA",
    "wof:name":"E8K 1P1",
    "wof:placetype":"postalcode"
},
  "geometry": {"coordinates":[-65.94972300000001,47.679349],"type":"Point"}
}