{
  "type": "Feature",
  "properties": {
    "iso:country":"CA",
    "wof:name":"T8N 5Z9",
    "wof:placetype":"postalcode"
},
  "geometry": {"coordinates":[-113.63345,53.639345],"type":"Point"}
}