{
  "type": "Feature",
  "properties": {
    "iso:country":"CA",
    "wof:name":"L7A 1W1",
    "wof:placetype":"postalcode"
},
  "geometry": {"coordinates":[-79.836912,43.690963],"type":"Point"}
}