{
  "type": "Feature",
  "properties": {
    "iso:country":"CA",
    "wof:name":"K7P 2Y7",
    "wof:placetype":"postalcode"
},
  "geometry": {"coordinates":[-76.61269,44.285151],"type":"Point"}
}