{
  "type": "Feature",
  "properties": {
    "iso:country":"CA",
    "wof:name":"L7K 0J4",
    "wof:placetype":"postalcode"
},
  "geometry": {"coordinates":[-80.027365,43.862874],"type":"Point"}
}