{
  "type": "Feature",
  "properties": {
    "iso:country":"CA",
    "wof:name":"T2A 3W4",
    "wof:placetype":"postalcode"
},
  "geometry": {"coordinates":[-113.94648599999999,51.049999],"type":"Point"}
}