{
  "type": "Feature",
  "properties": {
    "iso:country":"CA",
    "wof:name":"T7V 1L8",
    "wof:placetype":"postalcode"
},
  "geometry": {"coordinates":[-117.53126,53.663315],"type":"Point"}
}