{
  "type": "Feature",
  "properties": {
    "iso:country":"CA",
    "wof:name":"T2K 6E5",
    "wof:placetype":"postalcode"
},
  "geometry": {"coordinates":[-114.064643,51.11019],"type":"Point"}
}