{
  "type": "Feature",
  "properties": {
    "iso:country":"CA",
    "wof:name":"P0R 1J0",
    "wof:placetype":"postalcode"
},
  "geometry": {"coordinates":[-83.17765300000001,46.514518],"type":"Point"}
}