{
  "type": "Feature",
  "properties": {
    "iso:country":"CA",
    "wof:name":"B1M 1B7",
    "wof:placetype":"postalcode"
},
  "geometry": {"coordinates":[-60.064264,46.130786],"type":"Point"}
}