{
  "type": "Feature",
  "properties": {
    "iso:country":"CA",
    "wof:name":"J0N 1G5",
    "wof:placetype":"postalcode"
},
  "geometry": {"coordinates":[-74.023112,45.518844],"type":"Point"}
}