{
  "type": "Feature",
  "properties": {
    "iso:country":"CA",
    "wof:name":"R3N 0W8",
    "wof:placetype":"postalcode"
},
  "geometry": {"coordinates":[-97.19629999999999,49.863073],"type":"Point"}
}