{
  "type": "Feature",
  "properties": {
    "iso:country":"CA",
    "wof:name":"P0W 1M0",
    "wof:placetype":"postalcode"
},
  "geometry": {"coordinates":[-93.73375299999999,48.799062],"type":"Point"}
}