{
  "type": "Feature",
  "properties": {
    "iso:country":"CA",
    "wof:name":"J2E 1M7",
    "wof:placetype":"postalcode"
},
  "geometry": {"coordinates":[-72.535341,45.908692],"type":"Point"}
}