{
  "type": "Feature",
  "properties": {
    "iso:country":"CA",
    "wof:name":"N8T 2X5",
    "wof:placetype":"postalcode"
},
  "geometry": {"coordinates":[-82.948815,42.303779],"type":"Point"}
}