{
  "type": "Feature",
  "properties": {
    "iso:country":"CA",
    "wof:name":"P7J 1A7",
    "wof:placetype":"postalcode"
},
  "geometry": {"coordinates":[-89.3069,48.291463],"type":"Point"}
}