{
  "type": "Feature",
  "properties": {
    "iso:country":"CA",
    "wof:name":"S4N 7J6",
    "wof:placetype":"postalcode"
},
  "geometry": {"coordinates":[-104.55637299999999,50.469416],"type":"Point"}
}