{
  "type": "Feature",
  "properties": {
    "iso:country":"CA",
    "wof:name":"P4R 1H7",
    "wof:placetype":"postalcode"
},
  "geometry": {"coordinates":[-81.389008,48.476004],"type":"Point"}
}