{
  "type": "Feature",
  "properties": {
    "iso:country":"CA",
    "wof:name":"V4V 2H3",
    "wof:placetype":"postalcode"
},
  "geometry": {"coordinates":[-119.405717,50.073481],"type":"Point"}
}