{
  "type": "Feature",
  "properties": {
    "iso:country":"CA",
    "wof:name":"M3M 1R1",
    "wof:placetype":"postalcode"
},
  "geometry": {"coordinates":[-79.49085100000001,43.728584],"type":"Point"}
}