{
  "type": "Feature",
  "properties": {
    "iso:country":"CA",
    "wof:name":"L5J 2N7",
    "wof:placetype":"postalcode"
},
  "geometry": {"coordinates":[-79.629583,43.509451],"type":"Point"}
}