{
  "type": "Feature",
  "properties": {
    "iso:country":"CA",
    "wof:name":"R3H 1H8",
    "wof:placetype":"postalcode"
},
  "geometry": {"coordinates":[-97.204915,49.906208],"type":"Point"}
}