{
  "type": "Feature",
  "properties": {
    "iso:country":"CA",
    "wof:name":"E5V 1K3",
    "wof:placetype":"postalcode"
},
  "geometry": {"coordinates":[-66.97924500000001,44.968295],"type":"Point"}
}