{
  "type": "Feature",
  "properties": {
    "iso:country":"CA",
    "wof:name":"T0G 1P0",
    "wof:placetype":"postalcode"
},
  "geometry": {"coordinates":[-114.420226,55.696599],"type":"Point"}
}