{
  "type": "Feature",
  "properties": {
    "iso:country":"CA",
    "wof:name":"S7J 2N2",
    "wof:placetype":"postalcode"
},
  "geometry": {"coordinates":[-106.625208,52.098504],"type":"Point"}
}