{
  "type": "Feature",
  "properties": {
    "iso:country":"CA",
    "wof:name":"E9A 1R4",
    "wof:placetype":"postalcode"
},
  "geometry": {"coordinates":[-64.879244,47.021389],"type":"Point"}
}