{
  "type": "Feature",
  "properties": {
    "iso:country":"CA",
    "wof:name":"M9W 1V4",
    "wof:placetype":"postalcode"
},
  "geometry": {"coordinates":[-79.587129,43.704284],"type":"Point"}
}