{
  "type": "Feature",
  "properties": {
    "iso:country":"CA",
    "wof:name":"B2X 1G8",
    "wof:placetype":"postalcode"
},
  "geometry": {"coordinates":[-63.533454,44.700483],"type":"Point"}
}