{
  "type": "Feature",
  "properties": {
    "iso:country":"CA",
    "wof:name":"V2T 5R3",
    "wof:placetype":"postalcode"
},
  "geometry": {"coordinates":[-122.34854,49.03842],"type":"Point"}
}