{
  "type": "Feature",
  "properties": {
    "iso:country":"CA",
    "wof:name":"N5C 4H4",
    "wof:placetype":"postalcode"
},
  "geometry": {"coordinates":[-80.88699,43.049672],"type":"Point"}
}