{
  "type": "Feature",
  "properties": {
    "iso:country":"CA",
    "wof:name":"V6Y 3A8",
    "wof:placetype":"postalcode"
},
  "geometry": {"coordinates":[-123.116953,49.159071],"type":"Point"}
}