{
  "type": "Feature",
  "properties": {
    "iso:country":"CA",
    "wof:name":"M3L 2E4",
    "wof:placetype":"postalcode"
},
  "geometry": {"coordinates":[-79.517186,43.727586],"type":"Point"}
}