{
  "type": "Feature",
  "properties": {
    "iso:country":"CA",
    "wof:name":"G6K 1S7",
    "wof:placetype":"postalcode"
},
  "geometry": {"coordinates":[-71.302252,46.686667],"type":"Point"}
}