{
  "type": "Feature",
  "properties": {
    "iso:country":"CA",
    "wof:name":"P8N 1P2",
    "wof:placetype":"postalcode"
},
  "geometry": {"coordinates":[-91.88605099999999,49.871395],"type":"Point"}
}