{
  "type": "Feature",
  "properties": {
    "iso:country":"CA",
    "wof:name":"E4E 3W7",
    "wof:placetype":"postalcode"
},
  "geometry": {"coordinates":[-65.390336,45.632216],"type":"Point"}
}