{
  "type": "Feature",
  "properties": {
    "iso:country":"CA",
    "wof:name":"L8S 4N5",
    "wof:placetype":"postalcode"
},
  "geometry": {"coordinates":[-79.91425700000001,43.261788],"type":"Point"}
}