{
  "type": "Feature",
  "properties": {
    "iso:country":"CA",
    "wof:name":"V9M 1R3",
    "wof:placetype":"postalcode"
},
  "geometry": {"coordinates":[-124.910568,49.686687],"type":"Point"}
}