{
  "type": "Feature",
  "properties": {
    "iso:country":"CA",
    "wof:name":"V6E 3V8",
    "wof:placetype":"postalcode"
},
  "geometry": {"coordinates":[-123.12973100000001,49.283388],"type":"Point"}
}