{
  "type": "Feature",
  "properties": {
    "iso:country":"CA",
    "wof:name":"H2E 2A7",
    "wof:placetype":"postalcode"
},
  "geometry": {"coordinates":[-73.610579,45.551177],"type":"Point"}
}