{
  "type": "Feature",
  "properties": {
    "iso:country":"CA",
    "wof:name":"P7K 1N7",
    "wof:placetype":"postalcode"
},
  "geometry": {"coordinates":[-89.348535,48.373823],"type":"Point"}
}