{
  "type": "Feature",
  "properties": {
    "iso:country":"CA",
    "wof:name":"J7N 1K1",
    "wof:placetype":"postalcode"
},
  "geometry": {"coordinates":[-74.103241,45.624183],"type":"Point"}
}