{
  "type": "Feature",
  "properties": {
    "iso:country":"CA",
    "wof:name":"P0Y 1A0",
    "wof:placetype":"postalcode"
},
  "geometry": {"coordinates":[-95.106797,49.708019],"type":"Point"}
}