{
  "type": "Feature",
  "properties": {
    "iso:country":"CA",
    "wof:name":"B2R 1A9",
    "wof:placetype":"postalcode"
},
  "geometry": {"coordinates":[-63.548194,44.757822],"type":"Point"}
}