{
  "type": "Feature",
  "properties": {
    "iso:country":"CA",
    "wof:name":"M2P 2C2",
    "wof:placetype":"postalcode"
},
  "geometry": {"coordinates":[-79.397935,43.752068],"type":"Point"}
}