{
  "type": "Feature",
  "properties": {
    "iso:country":"CA",
    "wof:name":"G0A 4S0",
    "wof:placetype":"postalcode"
},
  "geometry": {"coordinates":[-70.932936,47.730376],"type":"Point"}
}