{
  "type": "Feature",
  "properties": {
    "iso:country":"CA",
    "wof:name":"E3A 6A4",
    "wof:placetype":"postalcode"
},
  "geometry": {"coordinates":[-66.365728,46.037997],"type":"Point"}
}