{
  "type": "Feature",
  "properties": {
    "iso:country":"CA",
    "wof:name":"E2G 1G9",
    "wof:placetype":"postalcode"
},
  "geometry": {"coordinates":[-65.93183999999999,45.452199],"type":"Point"}
}