{
  "type": "Feature",
  "properties": {
    "iso:country":"CA",
    "wof:name":"H4G 1Z6",
    "wof:placetype":"postalcode"
},
  "geometry": {"coordinates":[-73.56961099999999,45.464493],"type":"Point"}
}