{
  "type": "Feature",
  "properties": {
    "iso:country":"CA",
    "wof:name":"P7G 1Z9",
    "wof:placetype":"postalcode"
},
  "geometry": {"coordinates":[-89.33772399999999,48.455979],"type":"Point"}
}