{
  "type": "Feature",
  "properties": {
    "iso:country":"CA",
    "wof:name":"R2W 5G7",
    "wof:placetype":"postalcode"
},
  "geometry": {"coordinates":[-97.139245,49.920399],"type":"Point"}
}