{
  "type": "Feature",
  "properties": {
    "iso:country":"CA",
    "wof:name":"E9H 1H1",
    "wof:placetype":"postalcode"
},
  "geometry": {"coordinates":[-65.027945,47.350201],"type":"Point"}
}