{
  "type": "Feature",
  "properties": {
    "iso:country":"CA",
    "wof:name":"N7L 5C3",
    "wof:placetype":"postalcode"
},
  "geometry": {"coordinates":[-82.202405,42.418259],"type":"Point"}
}