{
  "type": "Feature",
  "properties": {
    "iso:country":"CA",
    "wof:name":"V7T 2A1",
    "wof:placetype":"postalcode"
},
  "geometry": {"coordinates":[-123.141734,49.332595],"type":"Point"}
}