{
  "type": "Feature",
  "properties": {
    "iso:country":"CA",
    "wof:name":"K6V 6T5",
    "wof:placetype":"postalcode"
},
  "geometry": {"coordinates":[-75.690631,44.669847],"type":"Point"}
}