{
  "type": "Feature",
  "properties": {
    "iso:country":"CA",
    "wof:name":"S0C 2K0",
    "wof:placetype":"postalcode"
},
  "geometry": {"coordinates":[-102.42589700000001,49.405846],"type":"Point"}
}