{
  "type": "Feature",
  "properties": {
    "iso:country":"CA",
    "wof:name":"E2V 2V6",
    "wof:placetype":"postalcode"
},
  "geometry": {"coordinates":[-66.42063,45.786895],"type":"Point"}
}