{
  "type": "Feature",
  "properties": {
    "iso:country":"CA",
    "wof:name":"B1A 4P6",
    "wof:placetype":"postalcode"
},
  "geometry": {"coordinates":[-59.885974,46.17853],"type":"Point"}
}