{
  "type": "Feature",
  "properties": {
    "iso:country":"CA",
    "wof:name":"R0K 1X0",
    "wof:placetype":"postalcode"
},
  "geometry": {"coordinates":[-99.644231,49.354692],"type":"Point"}
}