{
  "type": "Feature",
  "properties": {
    "iso:country":"CA",
    "wof:name":"H7A 3L8",
    "wof:placetype":"postalcode"
},
  "geometry": {"coordinates":[-73.60727300000001,45.669022],"type":"Point"}
}