{
  "type": "Feature",
  "properties": {
    "iso:country":"CA",
    "wof:name":"M1L 4B2",
    "wof:placetype":"postalcode"
},
  "geometry": {"coordinates":[-79.284215,43.712173],"type":"Point"}
}