{
  "type": "Feature",
  "properties": {
    "iso:country":"CA",
    "wof:name":"J0Z 3R0",
    "wof:placetype":"postalcode"
},
  "geometry": {"coordinates":[-78.911933,47.140493],"type":"Point"}
}