{
  "type": "Feature",
  "properties": {
    "iso:country":"CA",
    "wof:name":"K2E 7V1",
    "wof:placetype":"postalcode"
},
  "geometry": {"coordinates":[-75.714229,45.343883],"type":"Point"}
}