{
  "type": "Feature",
  "properties": {
    "iso:country":"CA",
    "wof:name":"P0J 1J0",
    "wof:placetype":"postalcode"
},
  "geometry": {"coordinates":[-80.064944,47.590101],"type":"Point"}
}