{
  "type": "Feature",
  "properties": {
    "iso:country":"CA",
    "wof:name":"V5M 1E5",
    "wof:placetype":"postalcode"
},
  "geometry": {"coordinates":[-123.039823,49.260085],"type":"Point"}
}