{
  "type": "Feature",
  "properties": {
    "iso:country":"CA",
    "wof:name":"V2H 5K1",
    "wof:placetype":"postalcode"
},
  "geometry": {"coordinates":[-120.26362,50.744462],"type":"Point"}
}