{
  "type": "Feature",
  "properties": {
    "iso:country":"CA",
    "wof:name":"J8X 4H9",
    "wof:placetype":"postalcode"
},
  "geometry": {"coordinates":[-75.713414,45.438216],"type":"Point"}
}