{
  "type": "Feature",
  "properties": {
    "iso:country":"CA",
    "wof:name":"T1S 1E9",
    "wof:placetype":"postalcode"
},
  "geometry": {"coordinates":[-114.055668,50.703049],"type":"Point"}
}