{
  "type": "Feature",
  "properties": {
    "iso:country":"CA",
    "wof:name":"R3S 1B1",
    "wof:placetype":"postalcode"
},
  "geometry": {"coordinates":[-97.29337,49.825257],"type":"Point"}
}