{
  "type": "Feature",
  "properties": {
    "iso:country":"CA",
    "wof:name":"M1B 4J9",
    "wof:placetype":"postalcode"
},
  "geometry": {"coordinates":[-79.188405,43.811594],"type":"Point"}
}