{
  "type": "Feature",
  "properties": {
    "iso:country":"CA",
    "wof:name":"V9C 1W4",
    "wof:placetype":"postalcode"
},
  "geometry": {"coordinates":[-123.56034200000001,48.389562],"type":"Point"}
}