{
  "type": "Feature",
  "properties": {
    "iso:country":"CA",
    "wof:name":"G2E 1T9",
    "wof:placetype":"postalcode"
},
  "geometry": {"coordinates":[-71.35990200000001,46.808451],"type":"Point"}
}