{
  "type": "Feature",
  "properties": {
    "iso:country":"CA",
    "wof:name":"T5J 4S2",
    "wof:placetype":"postalcode"
},
  "geometry": {"coordinates":[-113.498397,53.542935],"type":"Point"}
}