{
  "type": "Feature",
  "properties": {
    "iso:country":"CA",
    "wof:name":"J0K 3E0",
    "wof:placetype":"postalcode"
},
  "geometry": {"coordinates":[-73.965892,46.927294],"type":"Point"}
}