{
  "type": "Feature",
  "properties": {
    "iso:country":"CA",
    "wof:name":"K9K 2L9",
    "wof:placetype":"postalcode"
},
  "geometry": {"coordinates":[-78.371118,44.278706],"type":"Point"}
}