{
  "type": "Feature",
  "properties": {
    "iso:country":"CA",
    "wof:name":"S9V 1T6",
    "wof:placetype":"postalcode"
},
  "geometry": {"coordinates":[-109.80299100000001,53.416358],"type":"Point"}
}