{
  "type": "Feature",
  "properties": {
    "iso:country":"CA",
    "wof:name":"E3Y 1C2",
    "wof:placetype":"postalcode"
},
  "geometry": {"coordinates":[-67.62067,47.154976],"type":"Point"}
}