{
  "type": "Feature",
  "properties": {
    "iso:country":"CA",
    "wof:name":"J9A 1R8",
    "wof:placetype":"postalcode"
},
  "geometry": {"coordinates":[-75.76362399999999,45.434775],"type":"Point"}
}