{
  "type": "Feature",
  "properties": {
    "iso:country":"CA",
    "wof:name":"J8B 1Y5",
    "wof:placetype":"postalcode"
},
  "geometry": {"coordinates":[-74.120963,45.971015],"type":"Point"}
}