{
  "type": "Feature",
  "properties": {
    "iso:country":"CA",
    "wof:name":"V4T 1P3",
    "wof:placetype":"postalcode"
},
  "geometry": {"coordinates":[-119.682495,49.856297],"type":"Point"}
}