{
  "type": "Feature",
  "properties": {
    "iso:country":"CA",
    "wof:name":"T3C 2A1",
    "wof:placetype":"postalcode"
},
  "geometry": {"coordinates":[-114.140136,51.047156],"type":"Point"}
}