{
  "type": "Feature",
  "properties": {
    "iso:country":"CA",
    "wof:name":"J4Y 3K2",
    "wof:placetype":"postalcode"
},
  "geometry": {"coordinates":[-73.455708,45.441521],"type":"Point"}
}