{
  "type": "Feature",
  "properties": {
    "iso:country":"CA",
    "wof:name":"M4H 1C3",
    "wof:placetype":"postalcode"
},
  "geometry": {"coordinates":[-79.345009,43.704224],"type":"Point"}
}