{
  "type": "Feature",
  "properties": {
    "iso:country":"CA",
    "wof:name":"G2K 2K2",
    "wof:placetype":"postalcode"
},
  "geometry": {"coordinates":[-71.30443699999999,46.854613],"type":"Point"}
}