{
  "type": "Feature",
  "properties": {
    "iso:country":"CA",
    "wof:name":"G1S 1K2",
    "wof:placetype":"postalcode"
},
  "geometry": {"coordinates":[-71.245626,46.792926],"type":"Point"}
}