{
  "type": "Feature",
  "properties": {
    "iso:country":"CA",
    "wof:name":"J7B 1M6",
    "wof:placetype":"postalcode"
},
  "geometry": {"coordinates":[-73.81535100000001,45.660004],"type":"Point"}
}