{
  "type": "Feature",
  "properties": {
    "iso:country":"CA",
    "wof:name":"K7G 2B4",
    "wof:placetype":"postalcode"
},
  "geometry": {"coordinates":[-76.210711,44.351404],"type":"Point"}
}