{
  "type": "Feature",
  "properties": {
    "iso:country":"CA",
    "wof:name":"V8G 5G5",
    "wof:placetype":"postalcode"
},
  "geometry": {"coordinates":[-128.711107,54.554171],"type":"Point"}
}