{
  "type": "Feature",
  "properties": {
    "iso:country":"CA",
    "wof:name":"L3K 3J3",
    "wof:placetype":"postalcode"
},
  "geometry": {"coordinates":[-79.20820999999999,42.910874],"type":"Point"}
}