{
  "type": "Feature",
  "properties": {
    "iso:country":"CA",
    "wof:name":"G6B 2M9",
    "wof:placetype":"postalcode"
},
  "geometry": {"coordinates":[-70.810057,45.548319],"type":"Point"}
}