{
  "type": "Feature",
  "properties": {
    "iso:country":"CA",
    "wof:name":"V5J 1Z7",
    "wof:placetype":"postalcode"
},
  "geometry": {"coordinates":[-122.992671,49.204082],"type":"Point"}
}