{
  "type": "Feature",
  "properties": {
    "iso:country":"CA",
    "wof:name":"N0A 1N2",
    "wof:placetype":"postalcode"
},
  "geometry": {"coordinates":[-79.99621399999999,42.901173],"type":"Point"}
}