{
  "type": "Feature",
  "properties": {
    "iso:country":"CA",
    "wof:name":"T1Y 1G8",
    "wof:placetype":"postalcode"
},
  "geometry": {"coordinates":[-113.95782199999999,51.081296],"type":"Point"}
}