{
  "type": "Feature",
  "properties": {
    "iso:country":"CA",
    "wof:name":"N4N 2M8",
    "wof:placetype":"postalcode"
},
  "geometry": {"coordinates":[-80.96704,44.159564],"type":"Point"}
}