{
  "type": "Feature",
  "properties": {
    "iso:country":"CA",
    "wof:name":"P1C 1E4",
    "wof:placetype":"postalcode"
},
  "geometry": {"coordinates":[-79.422293,46.338529],"type":"Point"}
}