{
  "type": "Feature",
  "properties": {
    "iso:country":"CA",
    "wof:name":"H2K 3X7",
    "wof:placetype":"postalcode"
},
  "geometry": {"coordinates":[-73.552063,45.530905],"type":"Point"}
}