{
  "type": "Feature",
  "properties": {
    "iso:country":"CA",
    "wof:name":"V0M 1H0",
    "wof:placetype":"postalcode"
},
  "geometry": {"coordinates":[-121.873942,49.546684],"type":"Point"}
}