{
  "type": "Feature",
  "properties": {
    "iso:country":"CA",
    "wof:name":"M9R 4E2",
    "wof:placetype":"postalcode"
},
  "geometry": {"coordinates":[-79.55633899999999,43.687992],"type":"Point"}
}