{
  "type": "Feature",
  "properties": {
    "iso:country":"CA",
    "wof:name":"A1W 4Y5",
    "wof:placetype":"postalcode"
},
  "geometry": {"coordinates":[-52.945245,47.509991],"type":"Point"}
}