{
  "type": "Feature",
  "properties": {
    "iso:country":"CA",
    "wof:name":"N5A 1C5",
    "wof:placetype":"postalcode"
},
  "geometry": {"coordinates":[-80.91062599999999,43.386765],"type":"Point"}
}