{
  "type": "Feature",
  "properties": {
    "iso:country":"CA",
    "wof:name":"G0L 2G0",
    "wof:placetype":"postalcode"
},
  "geometry": {"coordinates":[-69.108385,47.773201],"type":"Point"}
}