{
  "type": "Feature",
  "properties": {
    "iso:country":"CA",
    "wof:name":"H9H 3Z3",
    "wof:placetype":"postalcode"
},
  "geometry": {"coordinates":[-73.866043,45.471757],"type":"Point"}
}