{
  "type": "Feature",
  "properties": {
    "iso:country":"CA",
    "wof:name":"T5T 0B2",
    "wof:placetype":"postalcode"
},
  "geometry": {"coordinates":[-113.657905,53.517609],"type":"Point"}
}