{
  "type": "Feature",
  "properties": {
    "iso:country":"CA",
    "wof:name":"S7N 5E3",
    "wof:placetype":"postalcode"
},
  "geometry": {"coordinates":[-106.608907,52.141626],"type":"Point"}
}