{
  "type": "Feature",
  "properties": {
    "iso:country":"CA",
    "wof:name":"J6J 4S1",
    "wof:placetype":"postalcode"
},
  "geometry": {"coordinates":[-73.72746600000001,45.379386],"type":"Point"}
}