{
  "type": "Feature",
  "properties": {
    "iso:country":"CA",
    "wof:name":"G9P 4L5",
    "wof:placetype":"postalcode"
},
  "geometry": {"coordinates":[-72.74996899999999,46.504646],"type":"Point"}
}