{
  "type": "Feature",
  "properties": {
    "iso:country":"CA",
    "wof:name":"V2S 2C1",
    "wof:placetype":"postalcode"
},
  "geometry": {"coordinates":[-122.287493,49.039282],"type":"Point"}
}