{
  "type": "Feature",
  "properties": {
    "iso:country":"CA",
    "wof:name":"N4W 1V3",
    "wof:placetype":"postalcode"
},
  "geometry": {"coordinates":[-80.88299499999999,43.689183],"type":"Point"}
}