{
  "type": "Feature",
  "properties": {
    "iso:country":"CA",
    "wof:name":"B1P 2Z5",
    "wof:placetype":"postalcode"
},
  "geometry": {"coordinates":[-60.170772,46.134738],"type":"Point"}
}