{
  "type": "Feature",
  "properties": {
    "iso:country":"CA",
    "wof:name":"V3L 3T9",
    "wof:placetype":"postalcode"
},
  "geometry": {"coordinates":[-122.900211,49.219662],"type":"Point"}
}