{
  "type": "Feature",
  "properties": {
    "iso:country":"CA",
    "wof:name":"N5Y 2E4",
    "wof:placetype":"postalcode"
},
  "geometry": {"coordinates":[-81.230204,43.012513],"type":"Point"}
}