{
  "type": "Feature",
  "properties": {
    "iso:country":"CA",
    "wof:name":"E2N 1P3",
    "wof:placetype":"postalcode"
},
  "geometry": {"coordinates":[-65.92057200000001,45.324231],"type":"Point"}
}