{
  "type": "Feature",
  "properties": {
    "iso:country":"CA",
    "wof:name":"V1J 3G9",
    "wof:placetype":"postalcode"
},
  "geometry": {"coordinates":[-121.81769300000001,57.154807],"type":"Point"}
}