{
  "type": "Feature",
  "properties": {
    "iso:country":"CA",
    "wof:name":"G0H 1A0",
    "wof:placetype":"postalcode"
},
  "geometry": {"coordinates":[-67.530041,49.456536],"type":"Point"}
}