{
  "type": "Feature",
  "properties": {
    "iso:country":"CA",
    "wof:name":"L4N 5R6",
    "wof:placetype":"postalcode"
},
  "geometry": {"coordinates":[-79.705322,44.349669],"type":"Point"}
}