{
  "type": "Feature",
  "properties": {
    "iso:country":"CA",
    "wof:name":"J7Z 2C2",
    "wof:placetype":"postalcode"
},
  "geometry": {"coordinates":[-73.98510899999999,45.779821],"type":"Point"}
}