{
  "type": "Feature",
  "properties": {
    "iso:country":"CA",
    "wof:name":"T2T 2C7",
    "wof:placetype":"postalcode"
},
  "geometry": {"coordinates":[-114.104179,51.023436],"type":"Point"}
}