{
  "type": "Feature",
  "properties": {
    "iso:country":"CA",
    "wof:name":"J6W 3C4",
    "wof:placetype":"postalcode"
},
  "geometry": {"coordinates":[-73.61676199999999,45.707374],"type":"Point"}
}