{
  "type": "Feature",
  "properties": {
    "iso:country":"CA",
    "wof:name":"B4P 1P1",
    "wof:placetype":"postalcode"
},
  "geometry": {"coordinates":[-64.358662,45.021252],"type":"Point"}
}