{
  "type": "Feature",
  "properties": {
    "iso:country":"CA",
    "wof:name":"M4M 2V8",
    "wof:placetype":"postalcode"
},
  "geometry": {"coordinates":[-79.338932,43.657016],"type":"Point"}
}