{
  "type": "Feature",
  "properties": {
    "iso:country":"CA",
    "wof:name":"V4C 3C4",
    "wof:placetype":"postalcode"
},
  "geometry": {"coordinates":[-122.911894,49.155494],"type":"Point"}
}