{
  "type": "Feature",
  "properties": {
    "iso:country":"CA",
    "wof:name":"G5N 5W5",
    "wof:placetype":"postalcode"
},
  "geometry": {"coordinates":[-68.476564,48.369985],"type":"Point"}
}