{
  "type": "Feature",
  "properties": {
    "iso:country":"CA",
    "wof:name":"G7A 4B5",
    "wof:placetype":"postalcode"
},
  "geometry": {"coordinates":[-71.39037500000001,46.670259],"type":"Point"}
}