{
  "type": "Feature",
  "properties": {
    "iso:country":"CA",
    "wof:name":"S4T 2P1",
    "wof:placetype":"postalcode"
},
  "geometry": {"coordinates":[-104.664976,50.447826],"type":"Point"}
}