{
  "type": "Feature",
  "properties": {
    "iso:country":"CA",
    "wof:name":"A2H 7T1",
    "wof:placetype":"postalcode"
},
  "geometry": {"coordinates":[-57.76049,48.9443],"type":"Point"}
}