{
  "type": "Feature",
  "properties": {
    "iso:country":"CA",
    "wof:name":"T1G 2G5",
    "wof:placetype":"postalcode"
},
  "geometry": {"coordinates":[-112.070398,49.723795],"type":"Point"}
}