{
  "type": "Feature",
  "properties": {
    "iso:country":"CA",
    "wof:name":"V6X 1R5",
    "wof:placetype":"postalcode"
},
  "geometry": {"coordinates":[-123.116191,49.185205],"type":"Point"}
}