{
  "type": "Feature",
  "properties": {
    "iso:country":"CA",
    "wof:name":"G7X 8X6",
    "wof:placetype":"postalcode"
},
  "geometry": {"coordinates":[-71.411085,48.31355],"type":"Point"}
}