{
  "type": "Feature",
  "properties": {
    "iso:country":"CA",
    "wof:name":"G3A 2G8",
    "wof:placetype":"postalcode"
},
  "geometry": {"coordinates":[-71.509944,46.754551],"type":"Point"}
}