{
  "type": "Feature",
  "properties": {
    "iso:country":"CA",
    "wof:name":"G0G 2L0",
    "wof:placetype":"postalcode"
},
  "geometry": {"coordinates":[-63.471482,51.118792],"type":"Point"}
}