{
  "type": "Feature",
  "properties": {
    "iso:country":"CA",
    "wof:name":"N9A 6N3",
    "wof:placetype":"postalcode"
},
  "geometry": {"coordinates":[-83.022706,42.194185],"type":"Point"}
}