{
  "type": "Feature",
  "properties": {
    "iso:country":"CA",
    "wof:name":"G1C 6T3",
    "wof:placetype":"postalcode"
},
  "geometry": {"coordinates":[-71.200495,46.885318],"type":"Point"}
}