{
  "type": "Feature",
  "properties": {
    "iso:country":"CA",
    "wof:name":"T3M 0A8",
    "wof:placetype":"postalcode"
},
  "geometry": {"coordinates":[-113.95469199999999,50.876356],"type":"Point"}
}