{
  "type": "Feature",
  "properties": {
    "iso:country":"CA",
    "wof:name":"S4X 1S3",
    "wof:placetype":"postalcode"
},
  "geometry": {"coordinates":[-104.67028000000001,50.511639],"type":"Point"}
}