{
  "type": "Feature",
  "properties": {
    "iso:country":"CA",
    "wof:name":"N8M 2Z4",
    "wof:placetype":"postalcode"
},
  "geometry": {"coordinates":[-82.828226,42.14448],"type":"Point"}
}