{
  "type": "Feature",
  "properties": {
    "iso:country":"CA",
    "wof:name":"J0W 1X0",
    "wof:placetype":"postalcode"
},
  "geometry": {"coordinates":[-75.698407,47.288311],"type":"Point"}
}