{
  "type": "Feature",
  "properties": {
    "iso:country":"CA",
    "wof:name":"K1N 8C4",
    "wof:placetype":"postalcode"
},
  "geometry": {"coordinates":[-75.683021,45.42957],"type":"Point"}
}