{
  "type": "Feature",
  "properties": {
    "iso:country":"CA",
    "wof:name":"S0H 2Z0",
    "wof:placetype":"postalcode"
},
  "geometry": {"coordinates":[-106.217724,49.835583],"type":"Point"}
}