{
  "type": "Feature",
  "properties": {
    "iso:country":"CA",
    "wof:name":"T2B 1V7",
    "wof:placetype":"postalcode"
},
  "geometry": {"coordinates":[-113.98047800000001,51.022986],"type":"Point"}
}