{
  "type": "Feature",
  "properties": {
    "iso:country":"CA",
    "wof:name":"L3Y 5Z2",
    "wof:placetype":"postalcode"
},
  "geometry": {"coordinates":[-79.37737199999999,44.049098],"type":"Point"}
}