{
  "type": "Feature",
  "properties": {
    "iso:country":"CA",
    "wof:name":"A5A 1B3",
    "wof:placetype":"postalcode"
},
  "geometry": {"coordinates":[-54.067335,48.180388],"type":"Point"}
}