{
  "type": "Feature",
  "properties": {
    "iso:country":"CA",
    "wof:name":"G3M 2V6",
    "wof:placetype":"postalcode"
},
  "geometry": {"coordinates":[-71.714011,46.690604],"type":"Point"}
}