{
  "type": "Feature",
  "properties": {
    "iso:country":"CA",
    "wof:name":"T3G 4X7",
    "wof:placetype":"postalcode"
},
  "geometry": {"coordinates":[-114.201453,51.139684],"type":"Point"}
}