{
  "type": "Feature",
  "properties": {
    "iso:country":"CA",
    "wof:name":"J5K 1Y4",
    "wof:placetype":"postalcode"
},
  "geometry": {"coordinates":[-74.140775,45.741665],"type":"Point"}
}