{
  "type": "Feature",
  "properties": {
    "iso:country":"CA",
    "wof:name":"E6K 1B7",
    "wof:placetype":"postalcode"
},
  "geometry": {"coordinates":[-67.05838,45.690099],"type":"Point"}
}