{
  "type": "Feature",
  "properties": {
    "iso:country":"CA",
    "wof:name":"G0E 1P0",
    "wof:placetype":"postalcode"
},
  "geometry": {"coordinates":[-65.361465,48.919943],"type":"Point"}
}