{
  "type": "Feature",
  "properties": {
    "iso:country":"CA",
    "wof:name":"H3P 1S4",
    "wof:placetype":"postalcode"
},
  "geometry": {"coordinates":[-73.639318,45.521729],"type":"Point"}
}