{
  "type": "Feature",
  "properties": {
    "iso:country":"CA",
    "wof:name":"V7C 4H1",
    "wof:placetype":"postalcode"
},
  "geometry": {"coordinates":[-123.17214,49.162137],"type":"Point"}
}