{
  "type": "Feature",
  "properties": {
    "iso:country":"CA",
    "wof:name":"L0P 1J0",
    "wof:placetype":"postalcode"
},
  "geometry": {"coordinates":[-80.04129,43.509876],"type":"Point"}
}