{
  "type": "Feature",
  "properties": {
    "iso:country":"CA",
    "wof:name":"H8R 2R4",
    "wof:placetype":"postalcode"
},
  "geometry": {"coordinates":[-73.654664,45.395562],"type":"Point"}
}