{
  "type": "Feature",
  "properties": {
    "iso:country":"CA",
    "wof:name":"J5J 1M3",
    "wof:placetype":"postalcode"
},
  "geometry": {"coordinates":[-73.917357,45.830163],"type":"Point"}
}