{
  "type": "Feature",
  "properties": {
    "iso:country":"CA",
    "wof:name":"K7A 1X7",
    "wof:placetype":"postalcode"
},
  "geometry": {"coordinates":[-75.991101,44.974555],"type":"Point"}
}