{
  "type": "Feature",
  "properties": {
    "iso:country":"CA",
    "wof:name":"G2A 3B5",
    "wof:placetype":"postalcode"
},
  "geometry": {"coordinates":[-71.373257,46.868781],"type":"Point"}
}