{
  "type": "Feature",
  "properties": {
    "iso:country":"CA",
    "wof:name":"V3J 3W3",
    "wof:placetype":"postalcode"
},
  "geometry": {"coordinates":[-122.857263,49.259855],"type":"Point"}
}