{
  "type": "Feature",
  "properties": {
    "iso:country":"CA",
    "wof:name":"V0P 1G0",
    "wof:placetype":"postalcode"
},
  "geometry": {"coordinates":[-125.02385599999999,51.054429],"type":"Point"}
}