{
  "type": "Feature",
  "properties": {
    "iso:country":"CA",
    "wof:name":"G5B 1T1",
    "wof:placetype":"postalcode"
},
  "geometry": {"coordinates":[-67.033541,49.977929],"type":"Point"}
}