{
  "type": "Feature",
  "properties": {
    "iso:country":"CA",
    "wof:name":"A1V 1R7",
    "wof:placetype":"postalcode"
},
  "geometry": {"coordinates":[-54.554446,48.950071],"type":"Point"}
}