{
  "type": "Feature",
  "properties": {
    "iso:country":"CA",
    "wof:name":"G1K 7M1",
    "wof:placetype":"postalcode"
},
  "geometry": {"coordinates":[-71.23125,46.814273],"type":"Point"}
}