{
  "type": "Feature",
  "properties": {
    "iso:country":"CA",
    "wof:name":"G7G 3M4",
    "wof:placetype":"postalcode"
},
  "geometry": {"coordinates":[-71.06031299999999,48.451621],"type":"Point"}
}