{
  "type": "Feature",
  "properties": {
    "iso:country":"CA",
    "wof:name":"J2C 8A8",
    "wof:placetype":"postalcode"
},
  "geometry": {"coordinates":[-72.513378,45.884981],"type":"Point"}
}