{
  "type": "Feature",
  "properties": {
    "iso:country":"CA",
    "wof:name":"L1G 5P8",
    "wof:placetype":"postalcode"
},
  "geometry": {"coordinates":[-78.864831,43.916732],"type":"Point"}
}