{
  "type": "Feature",
  "properties": {
    "iso:country":"CA",
    "wof:name":"V3A 6X7",
    "wof:placetype":"postalcode"
},
  "geometry": {"coordinates":[-122.657037,49.089185],"type":"Point"}
}