{
  "type": "Feature",
  "properties": {
    "iso:country":"CA",
    "wof:name":"K1P 5R7",
    "wof:placetype":"postalcode"
},
  "geometry": {"coordinates":[-75.700785,45.423013],"type":"Point"}
}