{
  "type": "Feature",
  "properties": {
    "iso:country":"CA",
    "wof:name":"V7A 4Y1",
    "wof:placetype":"postalcode"
},
  "geometry": {"coordinates":[-123.11637,49.119581],"type":"Point"}
}