{
  "type": "Feature",
  "properties": {
    "iso:country":"CA",
    "wof:name":"T2R 0R6",
    "wof:placetype":"postalcode"
},
  "geometry": {"coordinates":[-114.076177,51.041049],"type":"Point"}
}