{
  "type": "Feature",
  "properties": {
    "iso:country":"CA",
    "wof:name":"L9H 1R3",
    "wof:placetype":"postalcode"
},
  "geometry": {"coordinates":[-79.970247,43.28191],"type":"Point"}
}