{
  "type": "Feature",
  "properties": {
    "iso:country":"CA",
    "wof:name":"G1P 2M2",
    "wof:placetype":"postalcode"
},
  "geometry": {"coordinates":[-71.30753300000001,46.808081],"type":"Point"}
}