{
  "type": "Feature",
  "properties": {
    "iso:country":"CA",
    "wof:name":"P1A 1H8",
    "wof:placetype":"postalcode"
},
  "geometry": {"coordinates":[-79.454712,46.271165],"type":"Point"}
}