{
  "type": "Feature",
  "properties": {
    "iso:country":"CA",
    "wof:name":"R2E 1E3",
    "wof:placetype":"postalcode"
},
  "geometry": {"coordinates":[-97.013693,49.989336],"type":"Point"}
}