{
  "type": "Feature",
  "properties": {
    "iso:country":"CA",
    "wof:name":"N5W 1H7",
    "wof:placetype":"postalcode"
},
  "geometry": {"coordinates":[-81.18281899999999,42.986695],"type":"Point"}
}