{
  "type": "Feature",
  "properties": {
    "iso:country":"CA",
    "wof:name":"T2L 0G3",
    "wof:placetype":"postalcode"
},
  "geometry": {"coordinates":[-114.11545,51.104511],"type":"Point"}
}