{
  "type": "Feature",
  "properties": {
    "iso:country":"CA",
    "wof:name":"B1Y 1C7",
    "wof:placetype":"postalcode"
},
  "geometry": {"coordinates":[-60.343503,46.269193],"type":"Point"}
}