{
  "type": "Feature",
  "properties": {
    "iso:country":"CA",
    "wof:name":"E4Y 2M2",
    "wof:placetype":"postalcode"
},
  "geometry": {"coordinates":[-65.381005,46.714901],"type":"Point"}
}