{
  "type": "Feature",
  "properties": {
    "iso:country":"CA",
    "wof:name":"L0H 1M0",
    "wof:placetype":"postalcode"
},
  "geometry": {"coordinates":[-79.130022,43.894281],"type":"Point"}
}