{
  "type": "Feature",
  "properties": {
    "iso:country":"CA",
    "wof:name":"M6E 2G2",
    "wof:placetype":"postalcode"
},
  "geometry": {"coordinates":[-79.45097800000001,43.687783],"type":"Point"}
}