{
  "type": "Feature",
  "properties": {
    "iso:country":"CA",
    "wof:name":"E9C 1E3",
    "wof:placetype":"postalcode"
},
  "geometry": {"coordinates":[-66.034825,46.510855],"type":"Point"}
}