{
  "type": "Feature",
  "properties": {
    "iso:country":"CA",
    "wof:name":"T9N 1X9",
    "wof:placetype":"postalcode"
},
  "geometry": {"coordinates":[-110.78284499999999,54.262697],"type":"Point"}
}