{
  "type": "Feature",
  "properties": {
    "iso:country":"CA",
    "wof:name":"J7L 3L1",
    "wof:placetype":"postalcode"
},
  "geometry": {"coordinates":[-73.650417,45.741794],"type":"Point"}
}