{
  "type": "Feature",
  "properties": {
    "iso:country":"CA",
    "wof:name":"J5W 6B6",
    "wof:placetype":"postalcode"
},
  "geometry": {"coordinates":[-73.39651600000001,45.851812],"type":"Point"}
}