{
  "type": "Feature",
  "properties": {
    "iso:country":"CA",
    "wof:name":"H4K 1E2",
    "wof:placetype":"postalcode"
},
  "geometry": {"coordinates":[-73.735435,45.52029],"type":"Point"}
}