{
  "type": "Feature",
  "properties": {
    "iso:country":"CA",
    "wof:name":"T7N 1G8",
    "wof:placetype":"postalcode"
},
  "geometry": {"coordinates":[-114.52124000000001,54.075963],"type":"Point"}
}