{
  "type": "Feature",
  "properties": {
    "iso:country":"CA",
    "wof:name":"J7G 2T5",
    "wof:placetype":"postalcode"
},
  "geometry": {"coordinates":[-73.843436,45.606908],"type":"Point"}
}