{
  "type": "Feature",
  "properties": {
    "iso:country":"CA",
    "wof:name":"R6W 2Y9",
    "wof:placetype":"postalcode"
},
  "geometry": {"coordinates":[-97.940708,49.147754],"type":"Point"}
}