{
  "type": "Feature",
  "properties": {
    "iso:country":"CA",
    "wof:name":"V2W 1L9",
    "wof:placetype":"postalcode"
},
  "geometry": {"coordinates":[-122.466829,49.207047],"type":"Point"}
}