{
  "type": "Feature",
  "properties": {
    "iso:country":"CA",
    "wof:name":"R2K 1E3",
    "wof:placetype":"postalcode"
},
  "geometry": {"coordinates":[-97.084346,49.921107],"type":"Point"}
}