{
  "type": "Feature",
  "properties": {
    "iso:country":"CA",
    "wof:name":"J6S 1X3",
    "wof:placetype":"postalcode"
},
  "geometry": {"coordinates":[-74.039728,45.259464],"type":"Point"}
}