{
  "type": "Feature",
  "properties": {
    "iso:country":"CA",
    "wof:name":"B1L 1C5",
    "wof:placetype":"postalcode"
},
  "geometry": {"coordinates":[-60.282173,46.052799],"type":"Point"}
}