{
  "type": "Feature",
  "properties": {
    "iso:country":"CA",
    "wof:name":"J4V 0A1",
    "wof:placetype":"postalcode"
},
  "geometry": {"coordinates":[-73.473608,45.482981],"type":"Point"}
}