{
  "type": "Feature",
  "properties": {
    "iso:country":"CA",
    "wof:name":"T3A 4M9",
    "wof:placetype":"postalcode"
},
  "geometry": {"coordinates":[-114.146,51.13584],"type":"Point"}
}