{
  "type": "Feature",
  "properties": {
    "iso:country":"CA",
    "wof:name":"J8C 1V9",
    "wof:placetype":"postalcode"
},
  "geometry": {"coordinates":[-74.31317799999999,46.050208],"type":"Point"}
}