{
  "type": "Feature",
  "properties": {
    "iso:country":"CA",
    "wof:name":"T5C 2C6",
    "wof:placetype":"postalcode"
},
  "geometry": {"coordinates":[-113.454908,53.599629],"type":"Point"}
}