{
  "type": "Feature",
  "properties": {
    "iso:country":"CA",
    "wof:name":"K8R 1C9",
    "wof:placetype":"postalcode"
},
  "geometry": {"coordinates":[-77.46830300000001,44.139627],"type":"Point"}
}