{
  "type": "Feature",
  "properties": {
    "iso:country":"CA",
    "wof:name":"G6X 1J2",
    "wof:placetype":"postalcode"
},
  "geometry": {"coordinates":[-71.261229,46.714905],"type":"Point"}
}