{
  "type": "Feature",
  "properties": {
    "iso:country":"CA",
    "wof:name":"V3Y 2S2",
    "wof:placetype":"postalcode"
},
  "geometry": {"coordinates":[-122.681307,49.256156],"type":"Point"}
}