{
  "type": "Feature",
  "properties": {
    "iso:country":"CA",
    "wof:name":"M8V 2N9",
    "wof:placetype":"postalcode"
},
  "geometry": {"coordinates":[-79.506096,43.602637],"type":"Point"}
}