{
  "type": "Feature",
  "properties": {
    "iso:country":"CA",
    "wof:name":"R2J 3V9",
    "wof:placetype":"postalcode"
},
  "geometry": {"coordinates":[-97.072418,49.867706],"type":"Point"}
}