{
  "type": "Feature",
  "properties": {
    "iso:country":"CA",
    "wof:name":"J9X 4T9",
    "wof:placetype":"postalcode"
},
  "geometry": {"coordinates":[-78.759243,48.172221],"type":"Point"}
}