{
  "type": "Feature",
  "properties": {
    "iso:country":"CA",
    "wof:name":"H1R 3R5",
    "wof:placetype":"postalcode"
},
  "geometry": {"coordinates":[-73.607868,45.586269],"type":"Point"}
}