{
  "type": "Feature",
  "properties": {
    "iso:country":"CA",
    "wof:name":"E4Z 4K2",
    "wof:placetype":"postalcode"
},
  "geometry": {"coordinates":[-65.416691,46.057519],"type":"Point"}
}