{
  "type": "Feature",
  "properties": {
    "iso:country":"CA",
    "wof:name":"J6A 2H6",
    "wof:placetype":"postalcode"
},
  "geometry": {"coordinates":[-73.458102,45.742158],"type":"Point"}
}