{
  "type": "Feature",
  "properties": {
    "iso:country":"CA",
    "wof:name":"T7S 1H3",
    "wof:placetype":"postalcode"
},
  "geometry": {"coordinates":[-115.758689,54.195444],"type":"Point"}
}