{
  "type": "Feature",
  "properties": {
    "iso:country":"CA",
    "wof:name":"V5N 4G9",
    "wof:placetype":"postalcode"
},
  "geometry": {"coordinates":[-123.066496,49.254824],"type":"Point"}
}