{
  "type": "Feature",
  "properties": {
    "iso:country":"CA",
    "wof:name":"P1H 1S8",
    "wof:placetype":"postalcode"
},
  "geometry": {"coordinates":[-79.15483999999999,45.379554],"type":"Point"}
}