{
  "type": "Feature",
  "properties": {
    "iso:country":"CA",
    "wof:name":"H4J 2B7",
    "wof:placetype":"postalcode"
},
  "geometry": {"coordinates":[-73.70877,45.530822],"type":"Point"}
}