{
  "type": "Feature",
  "properties": {
    "iso:country":"CA",
    "wof:name":"M1R 3Y1",
    "wof:placetype":"postalcode"
},
  "geometry": {"coordinates":[-79.299967,43.751725],"type":"Point"}
}