{
  "type": "Feature",
  "properties": {
    "iso:country":"CA",
    "wof:name":"T4J 1N6",
    "wof:placetype":"postalcode"
},
  "geometry": {"coordinates":[-113.690595,52.66609],"type":"Point"}
}