{
  "type": "Feature",
  "properties": {
    "iso:country":"CA",
    "wof:name":"M6H 2A1",
    "wof:placetype":"postalcode"
},
  "geometry": {"coordinates":[-79.43800899999999,43.665276],"type":"Point"}
}