{
  "type": "Feature",
  "properties": {
    "iso:country":"CA",
    "wof:name":"N5L 1G4",
    "wof:placetype":"postalcode"
},
  "geometry": {"coordinates":[-81.26273,42.68876],"type":"Point"}
}