{
  "type": "Feature",
  "properties": {
    "iso:country":"CA",
    "wof:name":"N8V 1A1",
    "wof:placetype":"postalcode"
},
  "geometry": {"coordinates":[-82.940541,42.27805],"type":"Point"}
}